AUTHORS
LICENSE
MANIFEST.in
README.rst
setup.py
phoneconfirmation/__init__.py
phoneconfirmation/admin.py
phoneconfirmation/forms.py
phoneconfirmation/managers.py
phoneconfirmation/models.py
phoneconfirmation/receivers.py
phoneconfirmation/signals.py
phoneconfirmation/sms.py
phoneconfirmation/twilio.py
phoneconfirmation/urls.py
phoneconfirmation/utils.py
phoneconfirmation/views.py
phoneconfirmation/templates/phoneconfirmation/_country_label.html
phoneconfirmation/templates/phoneconfirmation/message.txt
phoneconfirmation/tests/__init__.py
phoneconfirmation/tests/models.py
phoneconfirmation/tests/tests.py
phoneconfirmation/tests/urls.py
pinax_phone_confirmation.egg-info/PKG-INFO
pinax_phone_confirmation.egg-info/SOURCES.txt
pinax_phone_confirmation.egg-info/dependency_links.txt
pinax_phone_confirmation.egg-info/not-zip-safe
pinax_phone_confirmation.egg-info/top_level.txt